roadguard/__init__.py
roadguard/constant.py
roadguard/function.py
roadguard/feed/__init__.py
roadguard/feed/camera.py
roadguard/feed/file.py
roadguard/feed/parameter.py
roadguard/feed/speaker.py
roadguard/feed/audio/__init__.py
roadguard/feed/audio/function.py
roadguard/feed/audio/parameter.py
roadguard/feed/audio/prompt.py
roadguard/feed/core/__init__.py
roadguard/feed/core/struct.py
roadguard/feed/video/__init__.py
roadguard/feed/video/function.py
roadguard/feed/video/parameter.py
roadguard/feed/video/prompt.py
RoadGuard-0.0.2.dist-info/LICENSE
RoadGuard-0.0.2.dist-info/METADATA
RoadGuard-0.0.2.dist-info/WHEEL
RoadGuard-0.0.2.dist-info/top_level.txt
RoadGuard-0.0.2.dist-info/RECORD
